<?xml version="1.0" encoding="utf-8"?><!DOCTYPE nta PUBLIC '-//Uppaal Team//DTD Flat System 1.1//EN' 'http://www.it.uu.se/research/group/darts/uppaal/flat-1_1.dtd'><nta><declaration>// Place global declarations here.

// Channels between the customer Eric and the ATM 
chan bank_card,      
     request, // request for 10 euro by Eric to the ATM
     deposit,
     withdraw,
     cash,
     update,
     no_cash,
     completed,
     not_completed;

// Channels between the ATM and the bank 
chan ask_withdraw, // request to pay out 10 euro 
     ask_deposit,
     OK, 
     not_OK,
     deposited,
     not_deposited;</declaration><template><name x="5" y="5">Eric</name><declaration>
int cash_in_pocket=0;  // cash in Eric's pocket</declaration><location id="id0" x="-504" y="-264"></location><location id="id1" x="-208" y="-264"></location><location id="id2" x="-504" y="-88"></location><location id="id3" x="-208" y="-88"></location><location id="id4" x="-208" y="-176"></location><location id="id5" x="-360" y="-176"><name x="-400" y="-208">IS_AT_ATM</name></location><location id="id6" x="-504" y="-176"><name x="-576" y="-184">READY</name></location><init ref="id6"/><transition><source ref="id0"/><target ref="id6"/><label kind="synchronisation" x="-584" y="-240">bank_card?</label></transition><transition><source ref="id1"/><target ref="id0"/><label kind="guard" x="-416" y="-344">cash_in_pocket &lt; 10</label><label kind="synchronisation" x="-408" y="-360">not_completed!</label><nail x="-368" y="-320"/></transition><transition><source ref="id1"/><target ref="id0"/><label kind="guard" x="-416" y="-288">cash_in_pocket &gt;= 10</label><label kind="synchronisation" x="-384" y="-248">completed!</label><label kind="assignment" x="-472" y="-264">cash_in_pocket = cash_in_pocket - 10</label></transition><transition><source ref="id4"/><target ref="id1"/><label kind="synchronisation" x="-192" y="-224">deposit!</label></transition><transition><source ref="id3"/><target ref="id2"/><label kind="synchronisation" x="-392" y="-48">no_cash?</label><label kind="assignment" x="-464" y="-16">cash_in_pocket = cash_in_pocket</label><nail x="-368" y="-16"/></transition><transition><source ref="id2"/><target ref="id6"/><label kind="synchronisation" x="-584" y="-136">bank_card?</label></transition><transition><source ref="id3"/><target ref="id2"/><label kind="synchronisation" x="-384" y="-112">cash?</label><label kind="assignment" x="-464" y="-88">cash_in_pocket = cash_in_pocket+10</label></transition><transition><source ref="id4"/><target ref="id3"/><label kind="synchronisation" x="-200" y="-144">withdraw!</label></transition><transition><source ref="id5"/><target ref="id4"/><label kind="synchronisation" x="-312" y="-176">bank_card!</label></transition><transition><source ref="id6"/><target ref="id5"/></transition></template><template><name>ATM</name><declaration>
int in_till = 200; // amount of cash in the ATM's till</declaration><location id="id7" x="-216" y="24"></location><location id="id8" x="-544" y="24"></location><location id="id9" x="-656" y="-48"></location><location id="id10" x="-536" y="-120"></location><location id="id11" x="-216" y="-64"></location><location id="id12" x="-656" y="200"><name x="-792" y="192">ALMOST_READY</name></location><location id="id13" x="-448" y="200"></location><location id="id14" x="-216" y="248"></location><location id="id15" x="-216" y="136"></location><location id="id16" x="-376" y="312"><name x="-376" y="328">READY_TO_PAY_OUT</name></location><location id="id17" x="-544" y="312"></location><location id="id18" x="-424" y="80"></location><location id="id19" x="-656" y="80"><name x="-720" y="72">READY</name></location><init ref="id19"/><transition><source ref="id7"/><target ref="id11"/><label kind="synchronisation" x="-192" y="-24">ask_deposit!</label></transition><transition><source ref="id18"/><target ref="id7"/><label kind="synchronisation" x="-328" y="16">deposit?</label></transition><transition><source ref="id8"/><target ref="id9"/><label kind="synchronisation" x="-608" y="-40">not_deposited!</label></transition><transition><source ref="id11"/><target ref="id10"/><label kind="synchronisation" x="-432" y="-120">completed?</label></transition><transition><source ref="id9"/><target ref="id19"/><label kind="synchronisation" x="-736" y="8">bank_card!</label></transition><transition><source ref="id10"/><target ref="id9"/><label kind="synchronisation" x="-600" y="-88">deposited!</label></transition><transition><source ref="id11"/><target ref="id8"/><label kind="synchronisation" x="-448" y="-48">not_completed?</label></transition><transition><source ref="id15"/><target ref="id13"/><label kind="guard" x="-360" y="136">in_till &lt;= 0</label></transition><transition><source ref="id16"/><target ref="id17"/><label kind="synchronisation" x="-488" y="288">update?</label></transition><transition><source ref="id13"/><target ref="id12"/><label kind="synchronisation" x="-584" y="176">no_cash!</label></transition><transition><source ref="id12"/><target ref="id19"/><label kind="synchronisation" x="-736" y="128">bank_card!</label></transition><transition><source ref="id14"/><target ref="id13"/><label kind="synchronisation" x="-336" y="200">not_OK?</label></transition><transition><source ref="id17"/><target ref="id12"/><label kind="synchronisation" x="-648" y="248">cash!</label><label kind="assignment" x="-696" y="272">in_till := in_till -10</label></transition><transition><source ref="id14"/><target ref="id16"/><label kind="synchronisation" x="-328" y="256">OK?</label></transition><transition><source ref="id15"/><target ref="id14"/><label kind="guard" x="-184" y="200">in_till &gt; 0</label><label kind="synchronisation" x="-184" y="176">ask_withdraw!</label></transition><transition><source ref="id18"/><target ref="id15"/><label kind="synchronisation" x="-320" y="88">withdraw?</label></transition><transition><source ref="id19"/><target ref="id18"/><label kind="synchronisation" x="-576" y="56">bank_card?</label></transition></template><template><name>Bank</name><declaration>
int balance=80; // balance of Eric's bank account </declaration><location id="id20" x="-280" y="144"></location><location id="id21" x="-440" y="-64"></location><location id="id22" x="-168" y="144"></location><location id="id23" x="24" y="144"></location><location id="id24" x="24" y="64"></location><location id="id25" x="-224" y="-64"><name x="-234" y="-94">READY</name></location><location id="id26" x="24" y="-64"></location><location id="id27" x="-88" y="64"></location><init ref="id25"/><transition><source ref="id20"/><target ref="id25"/><label kind="assignment" x="-432" y="112">balance := balance + 10</label></transition><transition><source ref="id21"/><target ref="id25"/><label kind="synchronisation" x="-392" y="16">not_deposited?</label><nail x="-344" y="16"/></transition><transition><source ref="id21"/><target ref="id20"/><label kind="synchronisation" x="-520" y="48">deposited?</label><nail x="-440" y="144"/></transition><transition><source ref="id25"/><target ref="id21"/><label kind="synchronisation" x="-376" y="-88">ask_deposit?</label></transition><transition><source ref="id22"/><target ref="id25"/></transition><transition><source ref="id23"/><target ref="id22"/><label kind="synchronisation" x="-96" y="152">update!</label><label kind="assignment" x="-136" y="112">balance := balance - 10</label></transition><transition><source ref="id27"/><target ref="id25"/><label kind="synchronisation" x="-160" y="-24">not_OK!</label></transition><transition><source ref="id24"/><target ref="id23"/><label kind="synchronisation" x="32" y="96">OK!</label></transition><transition><source ref="id26"/><target ref="id24"/><label kind="guard" x="32" y="-16">balance &gt;= 10</label></transition><transition><source ref="id26"/><target ref="id27"/><label kind="guard" x="-96" y="-48">balance &lt; 10</label></transition><transition><source ref="id25"/><target ref="id26"/><label kind="synchronisation" x="-144" y="-88">ask_withdraw?</label></transition></template><system>

// The system consists of Eric, an ATM, and a Back.

// There is only interaction between Eric and the ATM 
// and between the ATM and the Bank. 

system Eric, Bank, ATM;

</system></nta>